LICENSE
MANIFEST.in
README.rst
setup.py
pyjs9/__init__.py
pyjs9.egg-info/PKG-INFO
pyjs9.egg-info/SOURCES.txt
pyjs9.egg-info/dependency_links.txt
pyjs9.egg-info/not-zip-safe
pyjs9.egg-info/requires.txt
pyjs9.egg-info/top_level.txt