Metadata-Version: 2.1
Name: pyjs9
Version: 3.8
Summary: Python/JS9 connection, with numpy and astropy/fits support
Home-page: https://js9.si.edu
Author: Eric Mandel
Author-email: saord@cfa.harvard.edu
License: MIT
Keywords: astronomy astrophysics image display
Platform: UNKNOWN
Classifier: Development Status :: 5 - Production/Stable
Classifier: License :: OSI Approved :: MIT License
Classifier: Programming Language :: Python :: 3
Classifier: Topic :: Scientific/Engineering :: Astronomy
Provides-Extra: all
